whois11/__init__.py
whois11/__version__.py
whois11/const.py
whois11/errors.py
whois11/whois.py
whois11/whois_server.py
whois11-0.0.9.dist-info/LICENSE
whois11-0.0.9.dist-info/METADATA
whois11-0.0.9.dist-info/WHEEL
whois11-0.0.9.dist-info/top_level.txt
whois11-0.0.9.dist-info/RECORD
